tooltree/__init__.py
tooltree/build.py
tooltree/colors.py
tooltree/defaults.py
tooltree/output.py
tooltree/py.typed
tooltree/types.py
tooltree/visualize.py
tooltree-0.1.3.dist-info/WHEEL
tooltree-0.1.3.dist-info/METADATA
tooltree-0.1.3.dist-info/RECORD
