Metadata-Version: 2.4
Name: tooltree
Version: 0.1.3
Summary: functions for creating treemap data visualizations
Requires-Python: >=3.9
Classifier: Development Status :: 4 - Beta
Classifier: Intended Audience :: Developers
Classifier: Intended Audience :: Financial and Insurance Industry
Classifier: Intended Audience :: Science/Research
Classifier: License :: OSI Approved :: Apache Software License
Classifier: License :: OSI Approved :: MIT License
Classifier: Natural Language :: English
Classifier: Operating System :: MacOS
Classifier: Operating System :: Microsoft :: Windows
Classifier: Operating System :: POSIX :: Linux
Classifier: Programming Language :: Python :: 3.7
Classifier: Programming Language :: Python :: 3.8
Classifier: Programming Language :: Python :: 3.9
Classifier: Programming Language :: Python :: 3.10
Classifier: Programming Language :: Python :: 3.11
Classifier: Programming Language :: Python :: 3.12
Classifier: Typing :: Typed
Requires-Dist: plotly>=6.3.0
Requires-Dist: polars>=1.33.1
Requires-Dist: toolstr>=0.9.11
Project-URL: Documentation, https://github.com/sslivkoff/tooltree
Project-URL: Source, https://github.com/sslivkoff/tooltree
